litepolis_middleware_rate_limiter/__init__.py
litepolis_middleware_rate_limiter/core.py
litepolis_middleware_rate_limiter/utils.py
litepolis_middleware_rate_limiter-0.0.1.dist-info/licenses/LICENSE
litepolis_middleware_rate_limiter-0.0.1.dist-info/METADATA
litepolis_middleware_rate_limiter-0.0.1.dist-info/WHEEL
litepolis_middleware_rate_limiter-0.0.1.dist-info/top_level.txt
litepolis_middleware_rate_limiter-0.0.1.dist-info/RECORD
