Metadata-Version: 2.4
Name: litepolis-middleware-rate-limiter
Version: 0.0.1
Summary: The rate limit middleware module for LitePolis
Home-page: https://github.com/NewJerseyStyle/LitePolis-middleware-rate-limiter
Author: NewJerseyStyle
License: MIT License
License-File: LICENSE
Requires-Dist: litepolis
Dynamic: author
Dynamic: description
Dynamic: description-content-type
Dynamic: home-page
Dynamic: license
Dynamic: license-file
Dynamic: requires-dist
Dynamic: summary
